client/__init__.py
client/client_side.py
client/setup.py
client/client/__init__.py
client/client/add_contact.py
client/client/client_database.py
client/client/del_contact.py
client/client/main_window.py
client/client/main_window_conv.py
client/client/start_dialog.py
client/client/transport.py
client/common/__init__.py
client/common/decos.py
client/common/descryptors.py
client/common/errors.py
client/common/metaclasses.py
client/common/utilities.py
client/common/variables.py
client/doc/__init__.py
client/doc/source/__init__.py
client/doc/source/conf.py
client/log/__init__.py
client/log/configs/__init__.py
client/log/configs/client_log_settings.py
client/log/configs/server_log_settings.py
client/unit_tests/__init__.py
client/unit_tests/test_client_side.py
client/unit_tests/test_server_side.py
client/unit_tests/test_utilities.py
beksilter_messenger_client-0.0.1.dist-info/METADATA
beksilter_messenger_client-0.0.1.dist-info/WHEEL
beksilter_messenger_client-0.0.1.dist-info/top_level.txt
beksilter_messenger_client-0.0.1.dist-info/RECORD
