Metadata-Version: 2.1
Name: beksilter-messenger-client
Version: 0.0.1
Summary: Beksilter_Pyqt_Messenger
Home-page: UNKNOWN
Author: Beksilter
Author-email: Beksilter@mail.ru
License: UNKNOWN
Platform: UNKNOWN
Requires-Dist: PyQt5
Requires-Dist: sqlalchemy
Requires-Dist: pycryptodome
Requires-Dist: pycryptodomex
